{
  "info": {
    "_postman_id": "3b603df5-f4b3-45ba-92f0-18045cd221b9",
    "name": "API Tareas Laravel",
    "schema": "https://schema.getpostman.com/json/collection/v2.1.0/collection.json",
    "_exporter_id": "23115047"
  },
  "item": [
    {
      "name": "Autenticacion",
      "item": [
        {
          "name": "Registro",
          "request": {
            "auth": {
              "type": "noauth"
            },
            "method": "POST",
            "header": [],
            "body": {
              "mode": "raw",
              "raw": "{\r\n  \"name\": \"Lissette\",\r\n  \"email\": \"lissette3@test.com\",\r\n  \"password\": \"12345678\"\r\n}",
              "options": {
                "raw": {
                  "language": "json"
                }
              }
            },
            "url": {
              "raw": "http://127.0.0.1:8000/api/register",
              "protocol": "http",
              "host": [
                "127",
                "0",
                "0",
                "1"
              ],
              "port": "8000",
              "path": [
                "api",
                "register"
              ]
            }
          },
          "response": []
        },
        {
          "name": "Login",
          "request": {
            "auth": {
              "type": "noauth"
            },
            "method": "POST",
            "header": [],
            "body": {
              "mode": "raw",
              "raw": "{\r\n  \"email\": \"lissette3@test.com\",\r\n  \"password\": \"12345678\"\r\n}",
              "options": {
                "raw": {
                  "language": "json"
                }
              }
            },
            "url": {
              "raw": "http://127.0.0.1:8000/api/login",
              "protocol": "http",
              "host": [
                "127",
                "0",
                "0",
                "1"
              ],
              "port": "8000",
              "path": [
                "api",
                "login"
              ]
            }
          },
          "response": []
        },
        {
          "name": "obtener usuario",
          "protocolProfileBehavior": {
            "disableBodyPruning": true
          },
          "request": {
            "auth": {
              "type": "bearer",
              "bearer": [
                {
                  "key": "token",
                  "value": "2|z4UYfoPJ4YWlQl5gTboIYcjS4dWEf71aMFUAlHm079f8ff38",
                  "type": "string"
                }
              ]
            },
            "method": "GET",
            "header": [],
            "body": {
              "mode": "raw",
              "raw": "",
              "options": {
                "raw": {
                  "language": "json"
                }
              }
            },
            "url": {
              "raw": "http://127.0.0.1:8000/api/me",
              "protocol": "http",
              "host": [
                "127",
                "0",
                "0",
                "1"
              ],
              "port": "8000",
              "path": [
                "api",
                "me"
              ]
            }
          },
          "response": []
        },
        {
          "name": "Logout",
          "request": {
            "auth": {
              "type": "bearer",
              "bearer": [
                {
                  "key": "token",
                  "value": "2|z4UYfoPJ4YWlQl5gTboIYcjS4dWEf71aMFUAlHm079f8ff38",
                  "type": "string"
                }
              ]
            },
            "method": "POST",
            "header": [],
            "body": {
              "mode": "raw",
              "raw": "",
              "options": {
                "raw": {
                  "language": "json"
                }
              }
            },
            "url": {
              "raw": "http://127.0.0.1:8000/api/logout",
              "protocol": "http",
              "host": [
                "127",
                "0",
                "0",
                "1"
              ],
              "port": "8000",
              "path": [
                "api",
                "logout"
              ]
            }
          },
          "response": []
        }
      ]
    },
    {
      "name": "Tareas",
      "item": [
        {
          "name": "Crear tarea",
          "request": {
            "auth": {
              "type": "bearer",
              "bearer": [
                {
                  "key": "token",
                  "value": "2|z4UYfoPJ4YWlQl5gTboIYcjS4dWEf71aMFUAlHm079f8ff38",
                  "type": "string"
                }
              ]
            },
            "method": "POST",
            "header": [],
            "body": {
              "mode": "raw",
              "raw": "{\r\n  \"title\": \"Tarea prueba\",\r\n  \"description\": \"Probando tags\",\r\n  \"status\": \"pending\"\r\n}",
              "options": {
                "raw": {
                  "language": "json"
                }
              }
            },
            "url": {
              "raw": "http://127.0.0.1:8000/api/tasks",
              "protocol": "http",
              "host": [
                "127",
                "0",
                "0",
                "1"
              ],
              "port": "8000",
              "path": [
                "api",
                "tasks"
              ]
            }
          },
          "response": []
        },
        {
          "name": "Listar tareas",
          "request": {
            "auth": {
              "type": "bearer",
              "bearer": [
                {
                  "key": "token",
                  "value": "3|UGIdL4vhxI3xIUMJw0Do7ulDVDjtzydtCoE7RR0t70995723",
                  "type": "string"
                }
              ]
            },
            "method": "GET",
            "header": [],
            "url": {
              "raw": "http://127.0.0.1:8000/api/tasks",
              "protocol": "http",
              "host": [
                "127",
                "0",
                "0",
                "1"
              ],
              "port": "8000",
              "path": [
                "api",
                "tasks"
              ]
            }
          },
          "response": []
        },
        {
          "name": "Ver tarea",
          "protocolProfileBehavior": {
            "disableBodyPruning": true
          },
          "request": {
            "auth": {
              "type": "bearer",
              "bearer": [
                {
                  "key": "token",
                  "value": "3|UGIdL4vhxI3xIUMJw0Do7ulDVDjtzydtCoE7RR0t70995723",
                  "type": "string"
                }
              ]
            },
            "method": "GET",
            "header": [],
            "body": {
              "mode": "raw",
              "raw": "",
              "options": {
                "raw": {
                  "language": "json"
                }
              }
            },
            "url": {
              "raw": "http://127.0.0.1:8000/api/tasks/1",
              "protocol": "http",
              "host": [
                "127",
                "0",
                "0",
                "1"
              ],
              "port": "8000",
              "path": [
                "api",
                "tasks",
                "1"
              ]
            }
          },
          "response": []
        },
        {
          "name": "Actualizar tarea",
          "request": {
            "auth": {
              "type": "bearer",
              "bearer": [
                {
                  "key": "token",
                  "value": "3|UGIdL4vhxI3xIUMJw0Do7ulDVDjtzydtCoE7RR0t70995723",
                  "type": "string"
                }
              ]
            },
            "method": "PUT",
            "header": [],
            "body": {
              "mode": "raw",
              "raw": "",
              "options": {
                "raw": {
                  "language": "json"
                }
              }
            },
            "url": {
              "raw": "http://127.0.0.1:8000/api/tasks/1",
              "protocol": "http",
              "host": [
                "127",
                "0",
                "0",
                "1"
              ],
              "port": "8000",
              "path": [
                "api",
                "tasks",
                "1"
              ]
            }
          },
          "response": []
        },
        {
          "name": "Eliminar tarea",
          "request": {
            "auth": {
              "type": "bearer",
              "bearer": [
                {
                  "key": "token",
                  "value": "3|UGIdL4vhxI3xIUMJw0Do7ulDVDjtzydtCoE7RR0t70995723",
                  "type": "string"
                }
              ]
            },
            "method": "DELETE",
            "header": [],
            "url": {
              "raw": "http://127.0.0.1:8000/api/tasks/1",
              "protocol": "http",
              "host": [
                "127",
                "0",
                "0",
                "1"
              ],
              "port": "8000",
              "path": [
                "api",
                "tasks",
                "1"
              ]
            }
          },
          "response": []
        }
      ]
    },
    {
      "name": "Tags",
      "item": [
        {
          "name": "Crear tag",
          "request": {
            "auth": {
              "type": "bearer",
              "bearer": [
                {
                  "key": "token",
                  "value": "2|z4UYfoPJ4YWlQl5gTboIYcjS4dWEf71aMFUAlHm079f8ff38",
                  "type": "string"
                }
              ]
            },
            "method": "POST",
            "header": [],
            "body": {
              "mode": "raw",
              "raw": "{\r\n  \"nombre\": \"Urgente\",\r\n  \"color\": \"#FF0000\"\r\n}",
              "options": {
                "raw": {
                  "language": "json"
                }
              }
            },
            "url": {
              "raw": "http://127.0.0.1:8000/api/tags",
              "protocol": "http",
              "host": [
                "127",
                "0",
                "0",
                "1"
              ],
              "port": "8000",
              "path": [
                "api",
                "tags"
              ]
            }
          },
          "response": []
        },
        {
          "name": "Asignar tag",
          "request": {
            "auth": {
              "type": "bearer",
              "bearer": [
                {
                  "key": "token",
                  "value": "2|z4UYfoPJ4YWlQl5gTboIYcjS4dWEf71aMFUAlHm079f8ff38",
                  "type": "string"
                }
              ]
            },
            "method": "POST",
            "header": [],
            "body": {
              "mode": "raw",
              "raw": "{\r\n  \"tags\": [1]\r\n}",
              "options": {
                "raw": {
                  "language": "json"
                }
              }
            },
            "url": {
              "raw": "http://127.0.0.1:8000/api/tasks/1/tags",
              "protocol": "http",
              "host": [
                "127",
                "0",
                "0",
                "1"
              ],
              "port": "8000",
              "path": [
                "api",
                "tasks",
                "1",
                "tags"
              ]
            }
          },
          "response": []
        },
        {
          "name": "Eliminar tag de tarea",
          "request": {
            "auth": {
              "type": "bearer",
              "bearer": [
                {
                  "key": "token",
                  "value": "2|z4UYfoPJ4YWlQl5gTboIYcjS4dWEf71aMFUAlHm079f8ff38",
                  "type": "string"
                }
              ]
            },
            "method": "DELETE",
            "header": [],
            "url": {
              "raw": "http://127.0.0.1:8000/api/tasks/1/tags/1",
              "protocol": "http",
              "host": [
                "127",
                "0",
                "0",
                "1"
              ],
              "port": "8000",
              "path": [
                "api",
                "tasks",
                "1",
                "tags",
                "1"
              ]
            }
          },
          "response": []
        },
        {
          "name": "Eliminar tag",
          "request": {
            "auth": {
              "type": "bearer",
              "bearer": [
                {
                  "key": "token",
                  "value": "2|z4UYfoPJ4YWlQl5gTboIYcjS4dWEf71aMFUAlHm079f8ff38",
                  "type": "string"
                }
              ]
            },
            "method": "DELETE",
            "header": [],
            "body": {
              "mode": "raw",
              "raw": "",
              "options": {
                "raw": {
                  "language": "json"
                }
              }
            },
            "url": {
              "raw": "http://127.0.0.1:8000/api/tags/1",
              "protocol": "http",
              "host": [
                "127",
                "0",
                "0",
                "1"
              ],
              "port": "8000",
              "path": [
                "api",
                "tags",
                "1"
              ]
            }
          },
          "response": []
        },
        {
          "name": "Listar tags",
          "request": {
            "auth": {
              "type": "bearer",
              "bearer": [
                {
                  "key": "token",
                  "value": "3|UGIdL4vhxI3xIUMJw0Do7ulDVDjtzydtCoE7RR0t70995723",
                  "type": "string"
                }
              ]
            },
            "method": "GET",
            "header": [],
            "url": {
              "raw": "http://127.0.0.1:8000/api/tags",
              "protocol": "http",
              "host": [
                "127",
                "0",
                "0",
                "1"
              ],
              "port": "8000",
              "path": [
                "api",
                "tags"
              ]
            }
          },
          "response": []
        }
      ]
    }
  ]
}